{
  "items": [
    {
      "name": "アキッチ",
      "file": "file:///android_asset/data/Akicchi001.jpg",
      "when": "2002年ごろ",
      "where": "香川",
      "hair": "長毛種",
      "color": "チャシロ"
    },
    {
      "name": "アキ",
      "file": "file:///android_asset/data/Aki001.jpg",
      "when": "2009年ごろ",
      "where": "香川",
      "hair": "長毛種",
      "color": "キジシロ"
    },
    {
      "name": "アメさん",
      "file": "file:///android_asset/data/Ame001.jpg",
      "when": "2010年ごろ",
      "where": "大阪の何処か",
      "hair": "短毛種",
      "color": "アメリカンショートヘアー"
    },
    {
      "name": "ブチ",
      "file": "file:///android_asset/data/Bucchii001.jpg",
      "when": "2010年ごろ",
      "where": "大阪の何処か",
      "hair": "短毛種",
      "color": "黒ブチ"
    },
    {
      "name": "ブッピー",
      "file": "file:///android_asset/data/Buppii001.jpg",
      "when": "2002年ごろ",
      "where": "香川",
      "hair": "短毛種",
      "color": "キジトラ"
    },
    {
      "name": "チャア",
      "file": "file:///android_asset/data/Chaa001.jpg",
      "when": "2006年ごろ",
      "where": "千丈寺湖",
      "hair": "短毛種",
      "color": "チャシロ"
    },
    {
      "name": "チャブチさん",
      "file": "file:///android_asset/data/Chabuchi001.jpg",
      "when": "2008年ごろ",
      "where": "京都の何処か",
      "hair": "短毛種",
      "color": "チャシロ"
    },
    {
      "name": "チャカさん",
      "file": "file:///android_asset/data/Chaka001.jpg",
      "when": "2015年ごろ",
      "where": "目黒区",
      "hair": "短毛種",
      "color": "チャシロ"
    },
    {
      "name": "茶縞さん",
      "file": "file:///android_asset/data/Chashima001.jpg",
      "when": "2017年ごろ",
      "where": "目黒区",
      "hair": "短毛種",
      "color": "キジトラ"
    },
    {
      "name": "チャトラン",
      "file": "file:///android_asset/data/Chatran001.jpg",
      "when": "2013年ごろ",
      "where": "大阪",
      "hair": "短毛種",
      "color": "チャトラ"
    },
    {
      "name": "チャワレさん",
      "file": "file:///android_asset/data/Chaware001.jpg",
      "when": "2016年ごろ",
      "where": "目黒区",
      "hair": "短毛種",
      "color": "キジシロ"
    },
    {
      "name": "クル縞さん",
      "file": "file:///android_asset/data/Curushima001.jpg",
      "when": "2016年ごろ",
      "where": "目黒区",
      "hair": "短毛種",
      "color": "キジトラ"
    },
    {
      "name": "ハチさん",
      "file": "file:///android_asset/data/Hacchii001.jpg",
      "when": "2016年ごろ",
      "where": "目黒区",
      "hair": "短毛種",
      "color": "ハチワレ"
    },
    {
      "name": "ハルッチ",
      "file": "file:///android_asset/data/Harucchi001.jpg",
      "when": "2002年ごろ",
      "where": "香川",
      "hair": "長毛種",
      "color": "キジトラ"
    },
    {
      "name": "フデちゃん",
      "file": "file:///android_asset/data/Hude001.jpg",
      "when": "2006年ごろ",
      "where": "香川",
      "hair": "短毛種",
      "color": "三毛"
    },
    {
      "name": "ジュン",
      "file": "file:///android_asset/data/Jun001.jpg",
      "when": "2006年ごろ",
      "where": "香川",
      "hair": "短毛種",
      "color": "キジトラ"
    },
    {
      "name": "ケッシー",
      "file": "file:///android_asset/data/Kesshii001.jpg",
      "when": "2012年ごろ",
      "where": "香川",
      "hair": "短毛種",
      "color": "キジトラ"
    },
    {
      "name": "コゲシマさん",
      "file": "file:///android_asset/data/Kogeshima001.jpg",
      "when": "2015年ごろ",
      "where": "目黒区",
      "hair": "短毛種",
      "color": "サビトラ"
    },
    {
      "name": "クロ",
      "file": "file:///android_asset/data/Kuro001.jpg",
      "when": "2012年ごろ",
      "where": "大阪",
      "hair": "短毛種",
      "color": "クロ"
    },
    {
      "name": "クロボス",
      "file": "file:///android_asset/data/Kurobosu001.jpg",
      "when": "2006年ごろ",
      "where": "千丈寺湖",
      "hair": "短毛種",
      "color": "クロ"
    },
    {
      "name": "黒井さん",
      "file": "file:///android_asset/data/Kuroi001.jpg",
      "when": "2016年ごろ",
      "where": "目黒区",
      "hair": "短毛種",
      "color": "クロ"
    },
    {
      "name": "キュピーン",
      "file": "file:///android_asset/data/Kyupiin001.jpg",
      "when": "2006年ごろ",
      "where": "大阪",
      "hair": "短毛種",
      "color": "チャトラ"
    },
    {
      "name": "マダラ",
      "file": "file:///android_asset/data/Madara001.jpg",
      "when": "2010年ごろ",
      "where": "大阪",
      "hair": "短毛種",
      "color": "グレートラ"
    },
    {
      "name": "ミケリン",
      "file": "file:///android_asset/data/Mikerin001.jpg",
      "when": "2016年ごろ",
      "where": "目黒区",
      "hair": "短毛種",
      "color": "三毛"
    },
    {
      "name": "ムラブチさん",
      "file": "file:///android_asset/data/Murabuchi001.jpg",
      "when": "2016年ごろ",
      "where": "目黒区",
      "hair": "短毛種",
      "color": "シャムブチ"
    },
    {
      "name": "ムラシマさん",
      "file": "file:///android_asset/data/Murashima001.jpg",
      "when": "2016年ごろ",
      "where": "目黒区",
      "hair": "短毛種",
      "color": "ムラシマ"
    },
    {
      "name": "ナッチ",
      "file": "file:///android_asset/data/Nacchi001.jpg",
      "when": "2002年ごろ",
      "where": "香川",
      "hair": "短毛種",
      "color": "シロ"
    },
    {
      "name": "オド縞さん",
      "file": "file:///android_asset/data/Odoshima001.jpg",
      "when": "2016年ごろ",
      "where": "目黒区",
      "hair": "短毛種",
      "color": "キジトラ"
    },
    {
      "name": "オシンコシンの猫",
      "file": "file:///android_asset/data/Oshinkoshin001.jpg",
      "where": "北海道オシンコシンの滝",
      "hair": "短毛種",
      "color": "チャトラ"
    },
    {
      "name": "サッシー",
      "file": "file:///android_asset/data/Sasshii001.jpg",
      "where": "大阪",
      "hair": "短毛種",
      "color": "サバトラ"
    },
    {
      "name": "シマブチさん",
      "file": "file:///android_asset/data/Shimabuchi001.jpg",
      "where": "大阪",
      "hair": "短毛種",
      "color": "キジシロ"
    },
    {
      "name": "白長さん",
      "file": "file:///android_asset/data/Shironaga001.jpg",
      "where": "目黒区",
      "hair": "長毛種",
      "color": "シロ"
    },
    {
      "name": "ウッシー",
      "file": "file:///android_asset/data/Usshi001.jpg",
      "where": "大阪",
      "hair": "短毛種",
      "color": "クロシロ"
    }
  ]
}